setup.cfg
setup.py
vancouver/__init__.py
vancouver/vancouver.py
vancouver.py.egg-info/PKG-INFO
vancouver.py.egg-info/SOURCES.txt
vancouver.py.egg-info/dependency_links.txt
vancouver.py.egg-info/not-zip-safe
vancouver.py.egg-info/requires.txt
vancouver.py.egg-info/top_level.txt