Metadata-Version: 2.1
Name: vancouver.py
Version: 0.0.7
Summary: [SV] Alikoon Vancouver
Home-page: UNKNOWN
Author: Allan BlackWell
Author-email: allan_blackwell@list.ru
License: AMB
Project-URL: Alikoon, https://discord.gg/7yn4X9kuHt
Platform: any
Classifier: License :: OSI Approved :: Apache Software License
Classifier: Development Status :: 5 - Production/Stable
Classifier: Operating System :: OS Independent
Classifier: Intended Audience :: Developers
Classifier: Topic :: Software Development :: Libraries
Classifier: Topic :: Software Development :: Libraries :: Python Modules
Classifier: Programming Language :: Python :: 3.6
Classifier: Programming Language :: Python :: 3.7
Classifier: Programming Language :: Python :: 3.8
Classifier: Programming Language :: Python :: 3.9
Classifier: Programming Language :: Python :: 3.10
Requires-Python: >=3.6, <4
